mcp_ai_agent_sdk/__init__.py
mcp_ai_agent_sdk/client.py
mcp_ai_agent_sdk/exceptions.py
mcp_ai_agent_sdk-1.0.4.dist-info/METADATA
mcp_ai_agent_sdk-1.0.4.dist-info/WHEEL
mcp_ai_agent_sdk-1.0.4.dist-info/top_level.txt
mcp_ai_agent_sdk-1.0.4.dist-info/RECORD
