Metadata-Version: 2.4
Name: mcp-ai-agent-sdk
Version: 1.0.4
Summary: AI Agent Python SDK - 让任何后台系统快速接入 AI Agent 能力
Author-email: AI Agent Team <support@ai-agent.com>
License: MIT
Project-URL: Homepage, https://wangyunge.top
Project-URL: Documentation, https://wangyunge.top/docs
Project-URL: Repository, https://github.com/your-org/ai-agent-sdk
Keywords: ai,agent,database,natural-language,sql
Classifier: Development Status :: 4 - Beta
Classifier: Intended Audience :: Developers
Classifier: License :: OSI Approved :: MIT License
Classifier: Operating System :: OS Independent
Classifier: Programming Language :: Python :: 3
Classifier: Programming Language :: Python :: 3.7
Classifier: Programming Language :: Python :: 3.8
Classifier: Programming Language :: Python :: 3.9
Classifier: Programming Language :: Python :: 3.10
Classifier: Programming Language :: Python :: 3.11
Classifier: Programming Language :: Python :: 3.12
Classifier: Topic :: Database
Classifier: Topic :: Scientific/Engineering :: Artificial Intelligence
Requires-Python: >=3.7
Requires-Dist: requests>=2.25.0
Provides-Extra: dev
Requires-Dist: pytest>=7.0.0; extra == "dev"
Requires-Dist: pytest-cov>=4.0.0; extra == "dev"
Dynamic: requires-python
